README.md
setup.cfg
setup.py
iqfeat/__init__.py
iqfeat.egg-info/PKG-INFO
iqfeat.egg-info/SOURCES.txt
iqfeat.egg-info/dependency_links.txt
iqfeat.egg-info/top_level.txt
iqfeat.egg-info/zip-safe