Metadata-Version: 2.1
Name: iqfeat
Version: 6.0.1
Summary: IQFeat
Home-page: UNKNOWN
Author: VZM Conflict checker
Author-email: python@verizonmedia.com
License: UNKNOWN
Platform: UNKNOWN
Requires-Python: >="3.6"
